jupytertoolbox/__init__.py
jupytertoolbox/handlers.py
jupytertoolbox/static/handlers.js
jupytertoolbox/static/index.js
jupytertoolbox-0.0.1a1.dev6.data/data/etc/jupyter/jupyter_notebook_config.d/jupytertoolbox.json
jupytertoolbox-0.0.1a1.dev6.data/data/etc/jupyter/nbconfig/notebook.d/jupytertoolbox.json
jupytertoolbox-0.0.1a1.dev6.data/data/share/jupyter/nbextensions/jupytertoolbox/handlers.js
jupytertoolbox-0.0.1a1.dev6.data/data/share/jupyter/nbextensions/jupytertoolbox/index.js
jupytertoolbox-0.0.1a1.dev6.dist-info/LICENSE
jupytertoolbox-0.0.1a1.dev6.dist-info/METADATA
jupytertoolbox-0.0.1a1.dev6.dist-info/WHEEL
jupytertoolbox-0.0.1a1.dev6.dist-info/top_level.txt
jupytertoolbox-0.0.1a1.dev6.dist-info/RECORD
